easy_fnc/__init__.py
easy_fnc/core_utils.py
easy_fnc/function_caller.py
easy_fnc/functions.py
easy_fnc/schemas.py
easy_fnc/utils.py
easy_fnc/models/__init__.py
easy_fnc/models/groq.py
easy_fnc/models/model.py
easy_fnc/models/ollama.py
easy_fnc/models/templates/__init__.py
easy_fnc-0.2.3.dist-info/LICENSE
easy_fnc-0.2.3.dist-info/METADATA
easy_fnc-0.2.3.dist-info/WHEEL
easy_fnc-0.2.3.dist-info/top_level.txt
easy_fnc-0.2.3.dist-info/RECORD
