Metadata-Version: 2.1
Name: easy_fnc
Version: 0.2.3
Summary: This package hopes to provide a modular and highly extendable interface to interact with LLMs via (multiple) function calling, easily.
Home-page: https://github.com/AtakanTekparmak/easy_fnc
Author: Atakan Tekparmak
Author-email: atakantekerparmak@gmail.com
License-File: LICENSE
Requires-Dist: ollama
Requires-Dist: groq
Requires-Dist: pydantic
